{"type": "FeatureCollection", "name": "field_data", "crs": {"type": "name", "properties": {"name": "urn:ogc:def:crs:OGC:1.3:CRS84"}}, "features": [{"type": "Feature", "properties": {"moisture": 0}, "geometry": {"type": "Point", "coordinates": [30.250466317024095, 49.96575297878594]}}]}